main.py
src/AI.py
src/Bishop.py
src/Board.py
src/Coordinate.py
src/InputParser.py
src/King.py
src/Knight.py
src/Move.py
src/MoveNode.py
src/Pawn.py
src/Piece.py
src/Queen.py
src/Rook.py
src/__init__.py
src/main.py
src/termcolor.py
src/termcolor_test.py
cl_chess-1.2.7.dist-info/LICENSE
cl_chess-1.2.7.dist-info/METADATA
cl_chess-1.2.7.dist-info/WHEEL
cl_chess-1.2.7.dist-info/entry_points.txt
cl_chess-1.2.7.dist-info/top_level.txt
cl_chess-1.2.7.dist-info/RECORD
