Metadata-Version: 2.1
Name: cl-chess
Version: 1.2.7
Summary: A program to play chess on the command line
Home-page: https://github.com/marcusbuffett/command-line-chess
Author: Marcus Buffett
Author-email: marcusbuffett@me.com
License: UNKNOWN
Keywords: chess,game
Platform: UNKNOWN
Classifier: Programming Language :: Python :: 3
Requires-Dist: termcolor
